{
  "schemaVersion": 1,
  "id": "impactfulweather",
  "version": "2.4.7",
  "name": "Biome Particle Weather",
  "description": "Replaces vanilla minecraft weather rendering with shiny new particle variants + a few other goodies!",
  "authors": [
    "shadowmaster435"
  ],
  "contact": {
    "issues": "https://github.com/shadowmaster435/Impactful_Weather/issues",
    "homepage": "https://www.curseforge.com/minecraft/mc-mods/biome-particle-weather"
  },
  "license": "GPLv3",
  "environment": "client",
  "icon": "assets/impactfulweather/icon.png",
  "entrypoints": {
    "client": [
      "shadowmaster435.impactfulweather.client.ImpactfulWeatherClient"
    ],
    "modmenu": [
      "shadowmaster435.impactfulweather.client.BPWModMenuIntegration"
    ]
  },
  "mixins": [
    "ImpactfulWeather.mixins.json"
  ],
  "depends": {
    "fabricloader": ">=0.13.0",
    "fabric": "*",
    "minecraft": "1.18.2",
    "cloth-config2": "*"
  },
  "custom": {
    "modmenu": {
        "id": "impactfulweather",
        "name": "Biome Particle Weather",
        "description": "Replaces vanilla minecraft weather rendering with shiny new particle variants + a few other goodies!",
        "icon": "assets/impactfulweather/icon.png"
      }
    }
}
